came/PARAMETERS.py
came/__init__.py
came/pipeline.py
came/sample_data.zip
came/datapair/__init__.py
came/datapair/aligned.py
came/datapair/unaligned.py
came/model/__init__.py
came/model/_minibatch.py
came/model/_predict.py
came/model/_utils.py
came/model/base_layers.py
came/model/cgc.py
came/model/cggc.py
came/model/heteroframe.py
came/model/hidden.py
came/model/loss.py
came/model/v0/__init__.py
came/model/v0/_minibatch.py
came/model/v0/_predict.py
came/model/v0/_utils.py
came/model/v0/base_layers.py
came/model/v0/cgc.py
came/model/v0/cggc.py
came/model/v0/heteroframe.py
came/model/v0/hidden.py
came/model/v0/loss.py
came/utils/__init__.py
came/utils/_alluvial.py
came/utils/_base_trainer.py
came/utils/_get_example_data.py
came/utils/_io_h5py.py
came/utils/analyze.py
came/utils/base.py
came/utils/downsample_counts.py
came/utils/evaluation.py
came/utils/plot.py
came/utils/preprocess.py
came/utils/train.py
came/utils/train_v0.py
came-0.1.13.dist-info/LICENSE
came-0.1.13.dist-info/METADATA
came-0.1.13.dist-info/WHEEL
came-0.1.13.dist-info/top_level.txt
came-0.1.13.dist-info/RECORD
