Metadata-Version: 2.1
Name: came
Version: 0.1.13
Summary: cell-type assignment and gene module extraction of scRNA-seq
Home-page: https://github.com/XingyanLiu/CAME
Author: Xingyan Liu
Author-email: 544568643@qq.com
License: MIT
Classifier: License :: OSI Approved :: MIT License
Classifier: Programming Language :: Python
Classifier: Programming Language :: Python :: 3
Classifier: Programming Language :: Python :: 3.8
Classifier: Programming Language :: Python :: Implementation :: CPython
Classifier: Programming Language :: Python :: Implementation :: PyPy
Requires-Python: >=3.8.0
License-File: LICENSE
Requires-Dist: scanpy
Requires-Dist: torch
Requires-Dist: dgl
